Metadata-Version: 2.1
Name: LibraCreditoPDF
Version: 0.0.1
Summary: Leitor de PDF extrato
Author: Matheus Nascimento
Author-email: matheuskater02@outlook.com
License: MIT License
Keywords: Libra crédito
License-File: LICENSE
Requires-Dist: tabula
Requires-Dist: PyPDF2
Requires-Dist: pandas
Requires-Dist: pdfminer
Requires-Dist: pdfminer.six
